{"Title": "v.clean", "Abstract": "Toolset for cleaning topology of vector map.", "Identifier": "grass7:v.clean", "Input": [[{"Title": "input"}, {"Abstract": "Layer to clean"}, {"Identifier": "input"}, {"Parameter type": "QgsProcessingParameterFeatureSource"}, {"Accepted data types": [{"str": "layer ID"}, {"str": "layer name"}, {"str": "layer source"}, "QgsProcessingFeatureSourceDefinition", "QgsProperty", "QgsVectorLayer"]}], [{"Title": "type"}, {"Abstract": "Input feature type"}, {"Identifier": "type"}, {"Parameter type": "QgsProcessingParameterEnum"}, {"Available values": [{"0": "point"}, {"1": "line"}, {"2": "boundary"}, {"3": "centroid"}, {"4": "area"}, {"5": "face"}, {"6": "kernel"}]}, {"Accepted data types": ["int", {"str": "as string representation of int, e.g. '1'"}, "QgsProperty"]}], [{"Title": "tool"}, {"Abstract": "Cleaning tool"}, {"Identifier": "tool"}, {"Parameter type": "QgsProcessingParameterEnum"}, {"Available values": [{"0": "break"}, {"1": "snap"}, {"2": "rmdangle"}, {"3": "chdangle"}, {"4": "rmbridge"}, {"5": "chbridge"}, {"6": "rmdupl"}, {"7": "rmdac"}, {"8": "bpol"}, {"9": "prune"}, {"10": "rmarea"}, {"11": "rmline"}, {"12": "rmsa"}]}, {"Accepted data types": ["int", {"str": "as string representation of int, e.g. '1'"}, "QgsProperty"]}], [{"Title": "threshold"}, {"Abstract": "Threshold (comma separated for each tool)"}, {"Identifier": "threshold"}, {"Parameter type": "QgsProcessingParameterString"}, {"Accepted data types": ["str", "QgsProperty"]}], [{"Title": "-b"}, {"Abstract": "Do not build topology for the output vector"}, {"Identifier": "-b"}, {"Parameter type": "QgsProcessingParameterBoolean"}, {"Accepted data types": ["bool", "int", "str", "QgsProperty"]}], [{"Title": "-c"}, {"Abstract": "Combine tools with recommended follow-up tools"}, {"Identifier": "-c"}, {"Parameter type": "QgsProcessingParameterBoolean"}, {"Accepted data types": ["bool", "int", "str", "QgsProperty"]}], [{"Title": "output"}, {"Abstract": "Cleaned"}, {"Identifier": "output"}, {"Parameter type": "QgsProcessingParameterVectorDestination"}, {"Accepted data types": ["str", "QgsProperty", "QgsProcessingOutputLayerDefinition"]}], [{"Title": "error"}, {"Abstract": "Errors"}, {"Identifier": "error"}, {"Parameter type": "QgsProcessingParameterVectorDestination"}, {"Accepted data types": ["str", "QgsProperty", "QgsProcessingOutputLayerDefinition"]}], [{"Title": "GRASS_REGION_PARAMETER"}, {"Abstract": "GRASS GIS 7 region extent"}, {"Identifier": "GRASS_REGION_PARAMETER"}, {"Parameter type": "QgsProcessingParameterExtent"}, {"Accepted data types": [{"str": "as comma delimited list of x min, x max, y min, y max. E.g. '4,10,101,105'"}, {"str": "layer ID. Extent of layer is used."}, {"str": "layer name. Extent of layer is used."}, {"str": "layer source. Extent of layer is used."}, {"QgsMapLayer": "Extent of layer is used"}, {"QgsProcessingFeatureSourceDefinition": "Extent of source is used"}, "QgsProperty", "QgsRectangle", "QgsReferencedRectangle", {"QgsGeometry": "bounding box of geometry is used"}]}], [{"Title": "GRASS_SNAP_TOLERANCE_PARAMETER"}, {"Abstract": "v.in.ogr snap tolerance (-1 = no snap)"}, {"Identifier": "GRASS_SNAP_TOLERANCE_PARAMETER"}, {"Parameter type": "QgsProcessingParameterNumber"}, {"Accepted data types": ["int", "float", "QgsProperty"]}], [{"Title": "GRASS_MIN_AREA_PARAMETER"}, {"Abstract": "v.in.ogr min area"}, {"Identifier": "GRASS_MIN_AREA_PARAMETER"}, {"Parameter type": "QgsProcessingParameterNumber"}, {"Accepted data types": ["int", "float", "QgsProperty"]}], [{"Title": "GRASS_OUTPUT_TYPE_PARAMETER"}, {"Abstract": "v.out.ogr output type"}, {"Identifier": "GRASS_OUTPUT_TYPE_PARAMETER"}, {"Parameter type": "QgsProcessingParameterEnum"}, {"Available values": [{"0": "auto"}, {"1": "point"}, {"2": "line"}, {"3": "area"}]}, {"Accepted data types": ["int", {"str": "as string representation of int, e.g. '1'"}, "QgsProperty"]}], [{"Title": "GRASS_VECTOR_DSCO"}, {"Abstract": "v.out.ogr output data source options (dsco)"}, {"Identifier": "GRASS_VECTOR_DSCO"}, {"Parameter type": "QgsProcessingParameterString"}, {"Accepted data types": ["str", "QgsProperty"]}], [{"Title": "GRASS_VECTOR_LCO"}, {"Abstract": "v.out.ogr output layer options (lco)"}, {"Identifier": "GRASS_VECTOR_LCO"}, {"Parameter type": "QgsProcessingParameterString"}, {"Accepted data types": ["str", "QgsProperty"]}], [{"Title": "GRASS_VECTOR_EXPORT_NOCAT"}, {"Abstract": "Also export features without category (not labeled). Otherwise only features with category are exported"}, {"Identifier": "GRASS_VECTOR_EXPORT_NOCAT"}, {"Parameter type": "QgsProcessingParameterBoolean"}, {"Accepted data types": ["bool", "int", "str", "QgsProperty"]}]], "Outputs": [[{"Title": "output"}, {"Abstract": "Cleaned"}, {"Parameter type": "QgsProcessingOutputVectorLayer"}], [{"Title": "error"}, {"Abstract": "Errors"}, {"Parameter type": "QgsProcessingOutputVectorLayer"}]]}