{"Title": "Transpose Rasters", "Abstract": "", "Identifier": "saga:transposerasters", "Input": [[{"Title": "GRIDS"}, {"Abstract": "Grids"}, {"Identifier": "GRIDS"}, {"Parameter type": "QgsProcessingParameterMultipleLayers"}, {"Accepted data types": [{"list[str]": "list of layer IDs"}, {"list[str]": "list of layer names"}, {"list[str]": "list of layer sources"}, "list[QgsMapLayer]", "QgsProperty"]}], [{"Title": "TRANSPOSED"}, {"Abstract": "Transposed Grids"}, {"Identifier": "TRANSPOSED"}, {"Parameter type": "QgsProcessingParameterRasterDestination"}, {"Accepted data types": ["str", "QgsProperty", "QgsProcessingOutputLayerDefinition"]}], [{"Title": "MIRROR_X"}, {"Abstract": "Mirror Horizontally"}, {"Identifier": "MIRROR_X"}, {"Parameter type": "QgsProcessingParameterBoolean"}, {"Accepted data types": ["bool", "int", "str", "QgsProperty"]}], [{"Title": "MIRROR_Y"}, {"Abstract": "Mirror Vertically"}, {"Identifier": "MIRROR_Y"}, {"Parameter type": "QgsProcessingParameterBoolean"}, {"Accepted data types": ["bool", "int", "str", "QgsProperty"]}]], "Outputs": [{"Title": "TRANSPOSED"}, {"Abstract": "Transposed Grids"}, {"Parameter type": "QgsProcessingOutputRasterLayer"}]}