{"Title": "Multilevel B-Spline from Raster Points", "Abstract": "", "Identifier": "saga:multilevelbsplinefromrasterpoints", "Input": [[{"Title": "GRID"}, {"Abstract": "Grid"}, {"Identifier": "GRID"}, {"Parameter type": "QgsProcessingParameterRasterLayer"}, {"Accepted data types": [{"str": "layer ID"}, {"str": "layer name"}, {"str": "layer source"}, "QgsProperty", "QgsRasterLayer"]}], [{"Title": "TARGET_USER_XMIN TARGET_USER_XMAX TARGET_USER_YMIN TARGET_USER_YMAX"}, {"Abstract": "Output extent"}, {"Identifier": "TARGET_USER_XMIN TARGET_USER_XMAX TARGET_USER_YMIN TARGET_USER_YMAX"}, {"Parameter type": "QgsProcessingParameterExtent"}, {"Accepted data types": [{"str": "as comma delimited list of x min, x max, y min, y max. E.g. '4,10,101,105'"}, {"str": "layer ID. Extent of layer is used."}, {"str": "layer name. Extent of layer is used."}, {"str": "layer source. Extent of layer is used."}, {"QgsMapLayer": "Extent of layer is used"}, {"QgsProcessingFeatureSourceDefinition": "Extent of source is used"}, "QgsProperty", "QgsRectangle", "QgsReferencedRectangle", {"QgsGeometry": "bounding box of geometry is used"}]}], [{"Title": "TARGET_USER_SIZE"}, {"Abstract": "Cellsize"}, {"Identifier": "TARGET_USER_SIZE"}, {"Parameter type": "QgsProcessingParameterNumber"}, {"Accepted data types": ["int", "float", "QgsProperty"]}], [{"Title": "TARGET_OUT_GRID"}, {"Abstract": "Target Grid"}, {"Identifier": "TARGET_OUT_GRID"}, {"Parameter type": "QgsProcessingParameterRasterDestination"}, {"Accepted data types": ["str", "QgsProperty", "QgsProcessingOutputLayerDefinition"]}], [{"Title": "METHOD"}, {"Abstract": "Refinement"}, {"Identifier": "METHOD"}, {"Parameter type": "QgsProcessingParameterEnum"}, {"Available values": [{"0": "[0] no"}, {"1": "[1] yes"}]}, {"Accepted data types": ["int", {"str": "as string representation of int, e.g. '1'"}, "QgsProperty"]}], [{"Title": "EPSILON"}, {"Abstract": "Threshold Error"}, {"Identifier": "EPSILON"}, {"Parameter type": "QgsProcessingParameterNumber"}, {"Accepted data types": ["int", "float", "QgsProperty"]}], [{"Title": "LEVEL_MAX"}, {"Abstract": "Maximum Level"}, {"Identifier": "LEVEL_MAX"}, {"Parameter type": "QgsProcessingParameterNumber"}, {"Accepted data types": ["int", "float", "QgsProperty"]}], [{"Title": "DATATYPE"}, {"Abstract": "Data Type"}, {"Identifier": "DATATYPE"}, {"Parameter type": "QgsProcessingParameterEnum"}, {"Available values": [{"0": "[0] same as input grid"}, {"1": "[1] 4 byte floating point number"}]}, {"Accepted data types": ["int", {"str": "as string representation of int, e.g. '1'"}, "QgsProperty"]}]], "Outputs": [{"Title": "TARGET_OUT_GRID"}, {"Abstract": "Target Grid"}, {"Parameter type": "QgsProcessingOutputRasterLayer"}]}