{"Title": "Geographic Coordinate Rasters", "Abstract": "", "Identifier": "saga:geographiccoordinaterasters", "Input": [[{"Title": "GRID"}, {"Abstract": "Grid"}, {"Identifier": "GRID"}, {"Parameter type": "QgsProcessingParameterRasterLayer"}, {"Accepted data types": [{"str": "layer ID"}, {"str": "layer name"}, {"str": "layer source"}, "QgsProperty", "QgsRasterLayer"]}], [{"Title": "LON"}, {"Abstract": "Longitude"}, {"Identifier": "LON"}, {"Parameter type": "QgsProcessingParameterRasterDestination"}, {"Accepted data types": ["str", "QgsProperty", "QgsProcessingOutputLayerDefinition"]}], [{"Title": "LAT"}, {"Abstract": "Latitude"}, {"Identifier": "LAT"}, {"Parameter type": "QgsProcessingParameterRasterDestination"}, {"Accepted data types": ["str", "QgsProperty", "QgsProcessingOutputLayerDefinition"]}]], "Outputs": [[{"Title": "LON"}, {"Abstract": "Longitude"}, {"Parameter type": "QgsProcessingOutputRasterLayer"}], [{"Title": "LAT"}, {"Abstract": "Latitude"}, {"Parameter type": "QgsProcessingOutputRasterLayer"}]]}