{"Title": "Successive Flow Routing", "Abstract": "", "Identifier": "saga:successiveflowrouting", "Input": [[{"Title": "DEM"}, {"Abstract": "DEM"}, {"Identifier": "DEM"}, {"Parameter type": "QgsProcessingParameterRasterLayer"}, {"Accepted data types": [{"str": "layer ID"}, {"str": "layer name"}, {"str": "layer source"}, "QgsProperty", "QgsRasterLayer"]}], [{"Title": "FLOW"}, {"Abstract": "Flow"}, {"Identifier": "FLOW"}, {"Parameter type": "QgsProcessingParameterRasterDestination"}, {"Accepted data types": ["str", "QgsProperty", "QgsProcessingOutputLayerDefinition"]}], [{"Title": "ITERATIONS"}, {"Abstract": "Iterations"}, {"Identifier": "ITERATIONS"}, {"Parameter type": "QgsProcessingParameterNumber"}, {"Accepted data types": ["int", "float", "QgsProperty"]}], [{"Title": "RUNOFF"}, {"Abstract": "Runoff"}, {"Identifier": "RUNOFF"}, {"Parameter type": "QgsProcessingParameterNumber"}, {"Accepted data types": ["int", "float", "QgsProperty"]}], [{"Title": "MANNING"}, {"Abstract": "Manning's Roughness"}, {"Identifier": "MANNING"}, {"Parameter type": "QgsProcessingParameterNumber"}, {"Accepted data types": ["int", "float", "QgsProperty"]}]], "Outputs": [{"Title": "FLOW"}, {"Abstract": "Flow"}, {"Parameter type": "QgsProcessingOutputRasterLayer"}]}