{"Title": "Geometric Figures", "Abstract": "", "Identifier": "saga:geometricfigures", "Input": [[{"Title": "RESULT"}, {"Abstract": "Result"}, {"Identifier": "RESULT"}, {"Parameter type": "QgsProcessingParameterRasterDestination"}, {"Accepted data types": ["str", "QgsProperty", "QgsProcessingOutputLayerDefinition"]}], [{"Title": "CELL_COUNT"}, {"Abstract": "Cell Count"}, {"Identifier": "CELL_COUNT"}, {"Parameter type": "QgsProcessingParameterNumber"}, {"Accepted data types": ["int", "float", "QgsProperty"]}], [{"Title": "CELL_SIZE"}, {"Abstract": "Cell Size"}, {"Identifier": "CELL_SIZE"}, {"Parameter type": "QgsProcessingParameterNumber"}, {"Accepted data types": ["int", "float", "QgsProperty"]}], [{"Title": "FIGURE"}, {"Abstract": "Figure"}, {"Identifier": "FIGURE"}, {"Parameter type": "QgsProcessingParameterEnum"}, {"Available values": [{"0": "[0] Cone (up)"}, {"1": "[1] Cone (down)"}, {"2": "[2] Plane"}]}, {"Accepted data types": ["int", {"str": "as string representation of int, e.g. '1'"}, "QgsProperty"]}], [{"Title": "PLANE"}, {"Abstract": "Direction of Plane [Degree]"}, {"Identifier": "PLANE"}, {"Parameter type": "QgsProcessingParameterNumber"}, {"Accepted data types": ["int", "float", "QgsProperty"]}]], "Outputs": [{"Title": "RESULT"}, {"Abstract": "Result"}, {"Parameter type": "QgsProcessingOutputRasterLayer"}]}